{
  "compatibility_date": "2025-10-08",
  "main": "src/index.ts",
  "name": "security-autoauth",
  "upload_source_maps": true,
  "kv_namespaces": [
    {
      "binding": "AUTH_STORAGE",
      "id": "615621dd86134200b31dbb86c05e97a6"
    }
  ],
  "d1_databases": [
    {
      "binding": "AUTH_DB",
      "database_name": "vvaroo-euserver-ch",
      "database_id": "694e5fc3-9b9b-4ca6-85f9-0e0264d21dd9"
    }
  ],
  "observability": {
    "enabled": true
  },
  "compatibility_flags": ["nodejs_compat"]
}
